setup.py
src/phylter/__init__.py
src/phylter/conditions.py
src/phylter/parser.py
src/phylter/query.py
src/phylter.egg-info/PKG-INFO
src/phylter.egg-info/SOURCES.txt
src/phylter.egg-info/dependency_links.txt
src/phylter.egg-info/not-zip-safe
src/phylter.egg-info/requires.txt
src/phylter.egg-info/top_level.txt
src/phylter/backends/__init__.py
src/phylter/backends/base.py
src/phylter/backends/django_backend.py
src/phylter/backends/objects.py