Metadata-Version: 1.1
Name: phylter
Version: 0.2.3
Summary: Library for a filter DSL in python
Home-page: https://ercpe.de/projects/phylter
Author: Johann Schmitz
Author-email: johann@j-schmitz.net
License: GPL-3
Download-URL: https://code.not-your-server.de/phylter.git/tags/0.2.3.tar.gz
Platform: UNKNOWN
